Pyscp_Api/api.py
pyscpapi-1.1.0.dist-info/LICENSE
pyscpapi-1.1.0.dist-info/WHEEL
pyscpapi-1.1.0.dist-info/METADATA
pyscpapi-1.1.0.dist-info/RECORD
