Metadata-Version: 2.1
Name: pyscpapi
Version: 1.1.0
Summary: SCP API for python (https://api.scpslgame.com/)
Home-page: https://github.com/LEv145/SCP-Secret-Laboratory-API-python-pyscpapi
License: MIT
Author: LEv145
Requires-Python: >=3.6,<4.0
Classifier: License :: OSI Approved :: MIT License
Classifier: Programming Language :: Python :: 3
Classifier: Programming Language :: Python :: 3.6
Classifier: Programming Language :: Python :: 3.7
Classifier: Programming Language :: Python :: 3.8
Classifier: Programming Language :: Python :: 3.9
Requires-Dist: ujson (>=4.0.1,<5.0.0)
Project-URL: Repository, https://github.com/LEv145/SCP-Secret-Laboratory-API-python-pyscpapi
